infotags.py
infotags-1.1.2.dist-info/DESCRIPTION.rst
infotags-1.1.2.dist-info/METADATA
infotags-1.1.2.dist-info/RECORD
infotags-1.1.2.dist-info/WHEEL
infotags-1.1.2.dist-info/metadata.json
infotags-1.1.2.dist-info/top_level.txt
